NeteaseCloudMusic/NeteaseCloudMusicApi.js
NeteaseCloudMusic/__init__.py
NeteaseCloudMusic/config.json
NeteaseCloudMusic/help.py
NeteaseCloudMusic/main.py
NeteaseCloudMusic/utils.py
NeteaseCloudMusic-0.1.10.dist-info/LICENSE
NeteaseCloudMusic-0.1.10.dist-info/METADATA
NeteaseCloudMusic-0.1.10.dist-info/WHEEL
NeteaseCloudMusic-0.1.10.dist-info/top_level.txt
NeteaseCloudMusic-0.1.10.dist-info/RECORD
